{
    "swagger": "2.0",
    "info": {
        "title": "Cosmo Messenger API",
        "contact": {},
        "version": "1.0"
    },
    "paths": {
        "/api/v1/auth/login": {
            "post": {
                "description": "Authenticates user and returns JWT tokens",
                "consumes": [
                    "application/json"
                ],
                "produces": [
                    "application/json"
                ],
                "tags": [
                    "auth"
                ],
                "summary": "User login",
                "parameters": [
                    {
                        "description": "User credentials",
                        "name": "input",
                        "in": "body",
                        "required": true,
                        "schema": {
                            "$ref": "#/definitions/auth_api.loginRequest"
                        }
                    }
                ],
                "responses": {
                    "200": {
                        "description": "OK",
                        "schema": {
                            "$ref": "#/definitions/auth_api.loginResponse"
                        }
                    },
                    "400": {
                        "description": "Bad Request",
                        "schema": {
                            "type": "object",
                            "additionalProperties": {
                                "type": "string"
                            }
                        }
                    },
                    "401": {
                        "description": "Unauthorized",
                        "schema": {
                            "type": "object",
                            "additionalProperties": {
                                "type": "string"
                            }
                        }
                    }
                }
            }
        },
        "/api/v1/auth/refresh": {
            "post": {
                "description": "Returns new access token by refresh token",
                "consumes": [
                    "application/json"
                ],
                "produces": [
                    "application/json"
                ],
                "tags": [
                    "auth"
                ],
                "summary": "User refresh token",
                "parameters": [
                    {
                        "description": "Refresh credentials",
                        "name": "input",
                        "in": "body",
                        "required": true,
                        "schema": {
                            "$ref": "#/definitions/auth_api.refreshRequest"
                        }
                    }
                ],
                "responses": {
                    "200": {
                        "description": "OK",
                        "schema": {
                            "$ref": "#/definitions/auth_api.refreshResponse"
                        }
                    },
                    "400": {
                        "description": "Bad Request",
                        "schema": {
                            "type": "object",
                            "additionalProperties": {
                                "type": "string"
                            }
                        }
                    },
                    "401": {
                        "description": "Unauthorized",
                        "schema": {
                            "type": "object",
                            "additionalProperties": {
                                "type": "string"
                            }
                        }
                    }
                }
            }
        },
        "/api/v1/auth/validate": {
            "post": {
                "description": "Returns userID if access token is valid",
                "consumes": [
                    "application/json"
                ],
                "produces": [
                    "application/json"
                ],
                "tags": [
                    "auth"
                ],
                "summary": "Validates users access token",
                "parameters": [
                    {
                        "description": "Access credentials",
                        "name": "input",
                        "in": "body",
                        "required": true,
                        "schema": {
                            "$ref": "#/definitions/auth_api.validateRequest"
                        }
                    }
                ],
                "responses": {
                    "200": {
                        "description": "OK",
                        "schema": {
                            "$ref": "#/definitions/auth_api.validateResponse"
                        }
                    },
                    "400": {
                        "description": "Bad Request",
                        "schema": {
                            "type": "object",
                            "additionalProperties": {
                                "type": "string"
                            }
                        }
                    },
                    "401": {
                        "description": "Unauthorized",
                        "schema": {
                            "type": "object",
                            "additionalProperties": {
                                "type": "string"
                            }
                        }
                    }
                }
            }
        },
        "/api/v1/messages/direct": {
            "post": {
                "security": [
                    {
                        "BearerAuth": []
                    }
                ],
                "description": "Send direct message",
                "consumes": [
                    "application/json"
                ],
                "produces": [
                    "application/json"
                ],
                "tags": [
                    "messages"
                ],
                "summary": "Message sending",
                "parameters": [
                    {
                        "description": "User data",
                        "name": "input",
                        "in": "body",
                        "required": true,
                        "schema": {
                            "$ref": "#/definitions/message_api.msgRequest"
                        }
                    }
                ],
                "responses": {
                    "201": {
                        "description": "Created",
                        "schema": {
                            "$ref": "#/definitions/message_api.msgResponse"
                        }
                    },
                    "400": {
                        "description": "Bad Request",
                        "schema": {
                            "type": "object",
                            "additionalProperties": {
                                "type": "string"
                            }
                        }
                    }
                }
            }
        },
        "/api/v1/users/delete": {
            "delete": {
                "security": [
                    {
                        "BearerAuth": []
                    }
                ],
                "description": "Deletes the currently authenticated user",
                "consumes": [
                    "application/json"
                ],
                "produces": [
                    "application/json"
                ],
                "tags": [
                    "users"
                ],
                "summary": "Delete current user",
                "responses": {
                    "200": {
                        "description": "OK",
                        "schema": {
                            "$ref": "#/definitions/user_api.deleteResponse"
                        }
                    },
                    "400": {
                        "description": "Bad Request",
                        "schema": {
                            "type": "object",
                            "additionalProperties": {
                                "type": "string"
                            }
                        }
                    },
                    "401": {
                        "description": "Unauthorized",
                        "schema": {
                            "type": "object",
                            "additionalProperties": {
                                "type": "string"
                            }
                        }
                    },
                    "403": {
                        "description": "Forbidden",
                        "schema": {
                            "type": "object",
                            "additionalProperties": {
                                "type": "string"
                            }
                        }
                    }
                }
            }
        },
        "/api/v1/users/delete/{user_id}": {
            "delete": {
                "security": [
                    {
                        "BearerAuth": []
                    }
                ],
                "description": "Deletes a user by username. Admin access required.",
                "consumes": [
                    "application/json"
                ],
                "produces": [
                    "application/json"
                ],
                "tags": [
                    "users"
                ],
                "summary": "Delete user by username (Admin only)",
                "parameters": [
                    {
                        "type": "string",
                        "description": "Username of the user to delete",
                        "name": "username",
                        "in": "path",
                        "required": true
                    }
                ],
                "responses": {
                    "200": {
                        "description": "OK",
                        "schema": {
                            "$ref": "#/definitions/user_api.deleteResponse"
                        }
                    },
                    "400": {
                        "description": "Bad Request",
                        "schema": {
                            "type": "object",
                            "additionalProperties": {
                                "type": "string"
                            }
                        }
                    },
                    "401": {
                        "description": "Unauthorized",
                        "schema": {
                            "type": "object",
                            "additionalProperties": {
                                "type": "string"
                            }
                        }
                    },
                    "403": {
                        "description": "Forbidden",
                        "schema": {
                            "type": "object",
                            "additionalProperties": {
                                "type": "string"
                            }
                        }
                    }
                }
            }
        },
        "/api/v1/users/get_info": {
            "get": {
                "description": "Returns information about a user by username",
                "produces": [
                    "application/json"
                ],
                "tags": [
                    "users"
                ],
                "summary": "Get info about user",
                "parameters": [
                    {
                        "type": "string",
                        "description": "Username",
                        "name": "username",
                        "in": "query",
                        "required": true
                    }
                ],
                "responses": {
                    "200": {
                        "description": "OK",
                        "schema": {
                            "$ref": "#/definitions/user_api.infoResponse"
                        }
                    },
                    "400": {
                        "description": "Bad Request",
                        "schema": {
                            "type": "object",
                            "additionalProperties": {
                                "type": "string"
                            }
                        }
                    },
                    "404": {
                        "description": "Not Found",
                        "schema": {
                            "type": "object",
                            "additionalProperties": {
                                "type": "string"
                            }
                        }
                    }
                }
            }
        },
        "/api/v1/users/get_usernames_list": {
            "get": {
                "description": "Returns paginated usernames list",
                "consumes": [
                    "application/json"
                ],
                "produces": [
                    "application/json"
                ],
                "tags": [
                    "users"
                ],
                "summary": "Get usernames list",
                "parameters": [
                    {
                        "type": "integer",
                        "default": 1,
                        "description": "Page number",
                        "name": "page",
                        "in": "query"
                    },
                    {
                        "type": "integer",
                        "default": 10,
                        "description": "Items per page",
                        "name": "count",
                        "in": "query"
                    }
                ],
                "responses": {
                    "200": {
                        "description": "OK",
                        "schema": {
                            "$ref": "#/definitions/user_api.usernamesListResponse"
                        }
                    },
                    "400": {
                        "description": "Bad Request",
                        "schema": {
                            "type": "object",
                            "additionalProperties": {
                                "type": "string"
                            }
                        }
                    },
                    "500": {
                        "description": "Internal Server Error",
                        "schema": {
                            "type": "object",
                            "additionalProperties": {
                                "type": "string"
                            }
                        }
                    }
                }
            }
        },
        "/api/v1/users/register": {
            "post": {
                "description": "Creates a new user in system",
                "consumes": [
                    "application/json"
                ],
                "produces": [
                    "application/json"
                ],
                "tags": [
                    "users"
                ],
                "summary": "User registration",
                "parameters": [
                    {
                        "description": "User data",
                        "name": "input",
                        "in": "body",
                        "required": true,
                        "schema": {
                            "$ref": "#/definitions/user_api.registerRequest"
                        }
                    }
                ],
                "responses": {
                    "201": {
                        "description": "Created",
                        "schema": {
                            "$ref": "#/definitions/user_api.registerResponse"
                        }
                    },
                    "400": {
                        "description": "Bad Request",
                        "schema": {
                            "type": "object",
                            "additionalProperties": {
                                "type": "string"
                            }
                        }
                    }
                }
            }
        }
    },
    "definitions": {
        "auth_api.loginRequest": {
            "type": "object",
            "properties": {
                "password": {
                    "type": "string"
                },
                "username": {
                    "type": "string"
                }
            }
        },
        "auth_api.loginResponse": {
            "type": "object",
            "properties": {
                "access_token": {
                    "type": "string"
                },
                "refresh_token": {
                    "type": "string"
                }
            }
        },
        "auth_api.refreshRequest": {
            "type": "object",
            "properties": {
                "refresh_token": {
                    "type": "string"
                }
            }
        },
        "auth_api.refreshResponse": {
            "type": "object",
            "properties": {
                "access_token": {
                    "type": "string"
                }
            }
        },
        "auth_api.validateRequest": {
            "type": "object",
            "properties": {
                "access_token": {
                    "type": "string"
                }
            }
        },
        "auth_api.validateResponse": {
            "type": "object",
            "properties": {
                "username": {
                    "type": "string"
                }
            }
        },
        "message_api.msgRequest": {
            "type": "object",
            "required": [
                "content",
                "receiver_id"
            ],
            "properties": {
                "content": {
                    "type": "string"
                },
                "receiver_id": {
                    "type": "string"
                }
            }
        },
        "message_api.msgResponse": {
            "type": "object",
            "properties": {
                "message": {
                    "type": "string"
                }
            }
        },
        "user_api.deleteResponse": {
            "type": "object",
            "properties": {
                "message": {
                    "type": "string"
                }
            }
        },
        "user_api.infoResponse": {
            "type": "object",
            "properties": {
                "bio": {
                    "type": "string"
                },
                "id": {
                    "type": "string"
                },
                "name": {
                    "type": "string"
                },
                "username": {
                    "type": "string"
                }
            }
        },
        "user_api.paginationMeta": {
            "type": "object",
            "properties": {
                "has_next": {
                    "type": "boolean"
                },
                "has_prev": {
                    "type": "boolean"
                },
                "page": {
                    "type": "integer"
                },
                "total": {
                    "type": "integer"
                },
                "total_pages": {
                    "type": "integer"
                }
            }
        },
        "user_api.registerRequest": {
            "type": "object",
            "required": [
                "name",
                "password",
                "username"
            ],
            "properties": {
                "bio": {
                    "type": "string"
                },
                "name": {
                    "type": "string"
                },
                "password": {
                    "type": "string"
                },
                "username": {
                    "type": "string"
                }
            }
        },
        "user_api.registerResponse": {
            "type": "object",
            "properties": {
                "message": {
                    "type": "string"
                }
            }
        },
        "user_api.usernameData": {
            "type": "object",
            "properties": {
                "id": {
                    "type": "string"
                },
                "username": {
                    "type": "string"
                }
            }
        },
        "user_api.usernamesListResponse": {
            "type": "object",
            "properties": {
                "data": {
                    "type": "array",
                    "items": {
                        "$ref": "#/definitions/user_api.usernameData"
                    }
                },
                "meta": {
                    "$ref": "#/definitions/user_api.paginationMeta"
                }
            }
        }
    },
    "securityDefinitions": {
        "BearerAuth": {
            "type": "apiKey",
            "name": "Authorization",
            "in": "header"
        }
    }
}